LICENSE
setup.py
RailWagonLocation.egg-info/PKG-INFO
RailWagonLocation.egg-info/SOURCES.txt
RailWagonLocation.egg-info/dependency_links.txt
RailWagonLocation.egg-info/not-zip-safe
RailWagonLocation.egg-info/requires.txt
RailWagonLocation.egg-info/top_level.txt
railwagonlocation/__init__.py