Metadata-Version: 2.1
Name: RailWagonLocation
Version: 1.0.0
Summary: Python client for the RailwagonLocation API.
Home-page: https://github.com/Odya-LLC/railwagonlocation
Author: odya
Author-email: mmuhtor@gmail.com
License: MIT
Platform: 3.8
Platform: 3.9
Platform: 3.10
Platform: 3.11
Platform: 3.12
Classifier: Environment :: Web Environment
Classifier: Intended Audience :: Developers
Classifier: License :: OSI Approved :: MIT License
Classifier: Operating System :: OS Independent
Classifier: Programming Language :: Python
Classifier: Topic :: Internet :: WWW/HTTP :: Dynamic Content
Classifier: Topic :: Software Development :: Libraries :: Python Modules
License-File: LICENSE
